README.txt
setup.py
Products/__init__.py
Products.CMFLDAP.egg-info/PKG-INFO
Products.CMFLDAP.egg-info/SOURCES.txt
Products.CMFLDAP.egg-info/dependency_links.txt
Products.CMFLDAP.egg-info/entry_points.txt
Products.CMFLDAP.egg-info/namespace_packages.txt
Products.CMFLDAP.egg-info/not-zip-safe
Products.CMFLDAP.egg-info/requires.txt
Products.CMFLDAP.egg-info/top_level.txt
Products/CMFLDAP/CHANGES.txt
Products/CMFLDAP/COPYRIGHT.txt
Products/CMFLDAP/HISTORY.txt
Products/CMFLDAP/INSTALL.txt
Products/CMFLDAP/LDAPMemberDataTool.py
Products/CMFLDAP/LDAPMembershipTool.py
Products/CMFLDAP/LICENSE.txt
Products/CMFLDAP/README.txt
Products/CMFLDAP/VERSION.txt
Products/CMFLDAP/__init__.py
Products/CMFLDAP/configure.zcml
Products/CMFLDAP/tool.gif
Products/CMFLDAP/help/Memberdatatool-Configuration.stx
Products/CMFLDAP/help/Membershiptool-Configuration.stx
Products/CMFLDAP/profiles/default/metadata.xml
Products/CMFLDAP/profiles/default/skins.xml
Products/CMFLDAP/profiles/default/toolset.xml
Products/CMFLDAP/skins/cmfldap/join_form.py
Products/CMFLDAP/skins/cmfldap/join_template.pt
Products/CMFLDAP/skins/cmfldap/members_add_control.py
Products/CMFLDAP/skins/cmfldap/personalize_form.pt
Products/CMFLDAP/tests/__init__.py
Products/CMFLDAP/tests/test_LDAPMemberDataTool.py
Products/CMFLDAP/tests/test_LDAPMembershipTool.py
Products/CMFLDAP/tests/test_functional.py
Products/CMFLDAP/www/cmfldap_contents.pt
Products/CMFLDAP/www/cmfldap_memberProperties.pt